sparc_assemble/__init__.py
sparc_assemble/core/__init__.py
sparc_assemble/core/kg.py
sparc_assemble/core/assembler/__init__.py
sparc_assemble/core/assembler/assemble_utils.py
sparc_assemble/core/assembler/assembler.py
sparc_assemble/core/assembler/sparql_queries.py
sparc_assemble/core/assembler/workflow.py
sparc_assemble/core/assembler/workflow_utils.py
sparc_assemble/plugin/__init__.py
sparc_assemble/plugin/workflow_hub.py
sparc_assemble/resources/__init__.py
sparc_assemble/utils/__init__.py
sparc_assemble-0.1.9.dist-info/LICENSE
sparc_assemble-0.1.9.dist-info/METADATA
sparc_assemble-0.1.9.dist-info/WHEEL
sparc_assemble-0.1.9.dist-info/top_level.txt
sparc_assemble-0.1.9.dist-info/RECORD
