Metadata-Version: 2.1
Name: sparc-assemble
Version: 0.1.9
Summary: A Python tool to find and automatically assemble tools and workflows to process SPARC datasets in accordance with FAIR principles.
Author: Thiranja Prasad Babarenda Gamage, Chinchien Lin, Jiali Xu, Mathilde Verlyck, Max Dang Vu
License: Apache-2.0
License-File: LICENSE
Requires-Dist: owlready2
Requires-Dist: scriptcwl
Requires-Dist: ruamel.yaml
Requires-Dist: thefuzz ==0.22.1
Requires-Dist: spacy
Requires-Dist: torch ==2.3.0
Requires-Dist: sentence-transformers
